full_adder/full_adder_pralay.v
module full_adder(
    input a,
    input b,
    input cin,
    output sum,
    output carry
);
    // Logic for full adder
    assign sum = a ^ b ^ cin;   // XOR for sum
    assign carry = (a & b) | (b & cin) | (a & cin);   // Carry logic
endmodule

full_adder/full_adder_pralay_tb.v
// full_adder_tb.v
`timescale 1ns/1ps
module full_adder_tb;

    reg a;
    reg b;
    reg cin;
    wire sum;
    wire carry;

    // Instantiate the full adder
    full_adder uut (
        .a(a),
        .b(b),
        .cin(cin),
        .sum(sum),
        .carry(carry)
    );

    // Test sequence
    initial begin
        $dumpfile("full_adder.vcd");   // VCD file for GTKWave
        $dumpvars(0, full_adder_tb);

        $display("A B Cin | Sum Carry");
        $display("--------------------");

        a = 0; b = 0; cin = 0; #10;
        $display("%b %b  %b  |  %b    %b", a, b, cin, sum, carry);

        a = 0; b = 0; cin = 1; #10;
        $display("%b %b  %b  |  %b    %b", a, b, cin, sum, carry);

        a = 0; b = 1; cin = 0; #10;
        $display("%b %b  %b  |  %b    %b", a, b, cin, sum, carry);

        a = 0; b = 1; cin = 1; #10;
        $display("%b %b  %b  |  %b    %b", a, b, cin, sum, carry);

        a = 1; b = 0; cin = 0; #10;
        $display("%b %b  %b  |  %b    %b", a, b, cin, sum, carry);

        a = 1; b = 0; cin = 1; #10;
        $display("%b %b  %b  |  %b    %b", a, b, cin, sum, carry);

        a = 1; b = 1; cin = 0; #10;
        $display("%b %b  %b  |  %b    %b", a, b, cin, sum, carry);

        a = 1; b = 1; cin = 1; #10;
        $display("%b %b  %b  |  %b    %b", a, b, cin, sum, carry);

        $finish;
    end

endmodule

full_adder/full_adder.vcd
$date
	Fri Feb 20 21:02:45 2026
$end
$version
	Icarus Verilog
$end
$timescale
	1ps
$end
$scope module full_adder_tb $end
$var wire 1 ! sum $end
$var wire 1 " carry $end
$var reg 1 # a $end
$var reg 1 $ b $end
$var reg 1 % cin $end
$scope module uut $end
$var wire 1 # a $end
$var wire 1 $ b $end
$var wire 1 " carry $end
$var wire 1 % cin $end
$var wire 1 ! sum $end
$upscope $end
$upscope $end
$enddefinitions $end
$comment Show the parameter values. $end
$dumpall
$end
#0
$dumpvars
0%
0$
0#
0"
0!
$end
#10000
1!
1%
#20000
0%
1$
#30000
1"
0!
1%
#40000
0"
1!
0%
0$
1#
#50000
1"
0!
1%
#60000
0%
1$
#70000
1!
1%
